aiohttp_middlewares/__init__.py
aiohttp_middlewares/annotations.py
aiohttp_middlewares/constants.py
aiohttp_middlewares/cors.py
aiohttp_middlewares/error.py
aiohttp_middlewares/https.py
aiohttp_middlewares/py.typed
aiohttp_middlewares/shield.py
aiohttp_middlewares/timeout.py
aiohttp_middlewares/utils.py
aiohttp_middlewares-2.2.1.dist-info/LICENSE
aiohttp_middlewares-2.2.1.dist-info/METADATA
aiohttp_middlewares-2.2.1.dist-info/WHEEL
aiohttp_middlewares-2.2.1.dist-info/RECORD
