Metadata-Version: 2.1
Name: aiohttp-middlewares
Version: 2.2.1
Summary: Collection of useful middlewares for aiohttp applications.
Home-page: https://igordavydenko.com/projects.html#aiohttp-middlewares
License: BSD-3-Clause
Keywords: aiohttp,aiohttp-server,middlewares,aiohttp-middlewares
Author: Igor Davydenko
Author-email: iam@igordavydenko.com
Requires-Python: >=3.7,<4.0
Classifier: Development Status :: 5 - Production/Stable
Classifier: Environment :: Web Environment
Classifier: Framework :: AsyncIO
Classifier: Framework :: aiohttp
Classifier: Intended Audience :: Developers
Classifier: License :: OSI Approved :: BSD License
Classifier: Operating System :: OS Independent
Classifier: Programming Language :: Python :: 3
Classifier: Programming Language :: Python :: 3.7
Classifier: Programming Language :: Python :: 3.8
Classifier: Programming Language :: Python :: 3.9
Classifier: Programming Language :: Python :: 3.10
Classifier: Programming Language :: Python :: 3.11
Classifier: Topic :: Internet :: WWW/HTTP
Classifier: Topic :: Internet :: WWW/HTTP :: WSGI :: Middleware
Classifier: Topic :: Utilities
Classifier: Typing :: Typed
Requires-Dist: aiohttp (>=3.8.1,<4.0.0)
Requires-Dist: async-timeout (>=4.0.2,<5.0.0)
Requires-Dist: yarl (>=1.5.1,<2.0.0)
Project-URL: Documentation, https://aiohttp-middlewares.readthedocs.io/
Project-URL: Repository, https://github.com/playpauseandstop/aiohttp-middlewares
